deepkyu_pypi_test/__init__.py
deepkyu_pypi_test-0.0.1.dist-info/METADATA
deepkyu_pypi_test-0.0.1.dist-info/WHEEL
deepkyu_pypi_test-0.0.1.dist-info/top_level.txt
deepkyu_pypi_test-0.0.1.dist-info/RECORD
