Metadata-Version: 2.1
Name: deepkyu-pypi-test
Version: 0.0.1
Summary: Test package
Home-page: 
Author: deepkyu
Author-email: hungury96@gmail.com
Requires-Python: >=3.8
Requires-Dist: numpy
